setup.py
hm_probability/Binomialdistribution.py
hm_probability/Gaussiandistribution.py
hm_probability/Generaldistribution.py
hm_probability/__init__.py
hm_probability.egg-info/PKG-INFO
hm_probability.egg-info/SOURCES.txt
hm_probability.egg-info/dependency_links.txt
hm_probability.egg-info/not-zip-safe
hm_probability.egg-info/top_level.txt