Metadata-Version: 1.0
Name: hm-probability
Version: 1.0
Summary: Gaussian distributions
Home-page: UNKNOWN
Author: Hardik Makwana during Udacity Course 
Author-email: UNKNOWN
License: UNKNOWN
Platform: UNKNOWN
